[
  {
    "id": 1,
    "slug": "tas-rajut-macrame",
    "name": "Tas Rajut Macrame Premium",
    "description": "Tas rajut macrame elegan dengan detail anyaman halus. Cocok untuk gaya bohemian dan kasual. Tali bahu adjustable dan lapisan dalam kain katun.",
    "price": 185000,
    "category": "Tas",
    "image": "/images/products/placeholder.svg",
    "isFeatured": true,
    "stock": 12
  },
  {
    "id": 2,
    "slug": "syal-rajut-chunky",
    "name": "Syal Rajut Chunky Wool",
    "description": "Syal rajut chunky dengan benang wool premium. Hangat dan nyaman untuk musim hujan. Tersedia dalam berbagai warna.",
    "price": 125000,
    "category": "Aksesoris",
    "image": "/images/products/placeholder.svg",
    "isFeatured": true,
    "stock": 20
  },
  {
    "id": 3,
    "slug": "boneka-amigurumi-bunny",
    "name": "Boneka Amigurumi Bunny",
    "description": "Boneka rajut amigurumi bentuk kelinci yang menggemaskan. Dibuat dengan benang katun berkualitas, aman untuk anak-anak.",
    "price": 95000,
    "category": "Boneka",
    "image": "/images/products/placeholder.svg",
    "isFeatured": true,
    "stock": 15
  },
  {
    "id": 4,
    "slug": "topi-bucket-rajut",
    "name": "Topi Bucket Rajut",
    "description": "Topi bucket rajut stylish dengan motif modern. Ringan dan breathable untuk aktivitas outdoor.",
    "price": 85000,
    "category": "Aksesoris",
    "image": "/images/products/placeholder.svg",
    "isFeatured": true,
    "stock": 18
  },
  {
    "id": 5,
    "slug": "dompet-rajut-clutch",
    "name": "Dompet Rajut Clutch",
    "description": "Dompet clutch rajut minimalis dengan zipper kuat. Desain compact namun muat banyak barang esensial.",
    "price": 75000,
    "category": "Tas",
    "image": "/images/products/placeholder.svg",
    "isFeatured": true,
    "stock": 25
  },
  {
    "id": 6,
    "slug": "sarung-bantal-rajut",
    "name": "Sarung Bantal Rajut Bohemian",
    "description": "Sarung bantal rajut dengan motif bohemian elegan. Ukuran 45x45cm, cocok untuk dekorasi ruangan.",
    "price": 110000,
    "category": "Home Decor",
    "image": "/images/products/placeholder.svg",
    "isFeatured": true,
    "stock": 10
  },
  {
    "id": 7,
    "slug": "tempat-tissue-rajut",
    "name": "Tempat Tissue Rajut",
    "description": "Tempat tissue rajut cantik untuk mempercantik meja. Tersedia berbagai warna yang bisa disesuaikan.",
    "price": 45000,
    "category": "Home Decor",
    "image": "/images/products/placeholder.svg",
    "isFeatured": false,
    "stock": 30
  },
  {
    "id": 8,
    "slug": "gantungan-kunci-amigurumi",
    "name": "Gantungan Kunci Amigurumi",
    "description": "Gantungan kunci rajut mini dengan berbagai karakter lucu. Cocok untuk souvenir atau hadiah.",
    "price": 25000,
    "category": "Aksesoris",
    "image": "/images/products/placeholder.svg",
    "isFeatured": false,
    "stock": 50
  },
  {
    "id": 9,
    "slug": "boneka-amigurumi-bear",
    "name": "Boneka Amigurumi Teddy Bear",
    "description": "Boneka beruang rajut dengan ekspresi menggemaskan. Ukuran 25cm, cocok untuk hadiah spesial.",
    "price": 135000,
    "category": "Boneka",
    "image": "/images/products/placeholder.svg",
    "isFeatured": false,
    "stock": 8
  },
  {
    "id": 10,
    "slug": "totebag-rajut-jumbo",
    "name": "Totebag Rajut Jumbo",
    "description": "Totebag rajut ukuran jumbo untuk kebutuhan sehari-hari. Kuat, tahan lama, dan ramah lingkungan.",
    "price": 165000,
    "category": "Tas",
    "image": "/images/products/placeholder.svg",
    "isFeatured": false,
    "stock": 14
  },
  {
    "id": 11,
    "slug": "coaster-rajut-set",
    "name": "Coaster Rajut Set (6 pcs)",
    "description": "Set tatakan gelas rajut isi 6 pcs dengan warna senada. Melindungi meja dari noda dan goresan.",
    "price": 55000,
    "category": "Home Decor",
    "image": "/images/products/placeholder.svg",
    "isFeatured": false,
    "stock": 22
  },
  {
    "id": 12,
    "slug": "headband-rajut",
    "name": "Headband Rajut Cute",
    "description": "Headband rajut dengan desain cantik dan nyaman dipakai. Elastis dan tidak membuat pusing.",
    "price": 35000,
    "category": "Aksesoris",
    "image": "/images/products/placeholder.svg",
    "isFeatured": false,
    "stock": 35
  }
]
